<PAMDataset>
  <PAMRasterBand band="1">
    <Histograms>
      <HistItem>
        <HistMin>-0.5</HistMin>
        <HistMax>249.5</HistMax>
        <BucketCount>250</BucketCount>
        <IncludeOutOfRange>1</IncludeOutOfRange>
        <Approximate>0</Approximate>
        <HistCounts>0|0|0|0|0|0|0|0|0|0|0|0|0|0|0|0|0|0|0|0|0|0|0|0|0|0|0|0|0|0|0|0|0|0|0|2|1|3|1|2|2|2|5|4|1|2|3|2|4|10|7|8|7|7|17|10|12|8|9|13|12|21|15|14|25|15|4|16|17|22|20|18|23|22|21|24|34|18|28|22|28|26|34|29|23|38|37|20|31|24|35|26|28|31|28|26|23|19|30|30|36|37|46|27|28|36|33|27|36|41|25|32|34|40|29|19|35|27|29|35|38|42|40|28|34|38|26|35|30|39|34|37|35|32|46|41|35|54|42|45|39|46|58|42|44|49|53|41|53|43|66|58|59|47|64|67|51|50|65|62|57|60|73|63|58|66|85|84|81|97|70|59|79|96|81|98|100|112|131|143|183|224|262|317|384|364|441|404|478|444|530|550|718|672|875|916|1305|1360|2023|1864|2601|2111|3083|2497|3037|2598|3214|2419|2905|2210|2313|1818|1935|1515|1599|1285|1143|1020|937|756|736|598|556|455|399|374|315|278|260|206|218|145|139|64|58|43|42|18|19|17|10|10|5|2|3|2|0|1|0|1</HistCounts>
      </HistItem>
    </Histograms>
    <Metadata>
      <MDI key="STATISTICS_COUNT">65536.000000</MDI>
      <MDI key="STATISTICS_COVARIANCES">575.1860469635019,464.0048443960429,465.0088307114268</MDI>
      <MDI key="STATISTICS_EXCLUDEDVALUES"></MDI>
      <MDI key="STATISTICS_MAXIMUM">249</MDI>
      <MDI key="STATISTICS_MEAN">199.89164733887</MDI>
      <MDI key="STATISTICS_MEDIAN">204.000000</MDI>
      <MDI key="STATISTICS_MINIMUM">35</MDI>
      <MDI key="STATISTICS_SKIPFACTORX">1</MDI>
      <MDI key="STATISTICS_SKIPFACTORY">1</MDI>
      <MDI key="STATISTICS_STDDEV">23.983036650172</MDI>
    </Metadata>
  </PAMRasterBand>
  <PAMRasterBand band="2">
    <Histograms>
      <HistItem>
        <HistMin>-0.5</HistMin>
        <HistMax>218.5</HistMax>
        <BucketCount>219</BucketCount>
        <IncludeOutOfRange>1</IncludeOutOfRange>
        <Approximate>0</Approximate>
        <HistCounts>0|0|0|0|0|0|0|0|0|0|0|0|0|0|0|0|0|0|0|0|0|0|0|0|0|0|0|0|0|0|0|1|2|1|3|4|12|21|49|42|96|107|134|144|166|178|213|198|187|191|185|152|176|140|158|136|167|147|156|137|133|115|122|139|127|132|126|132|145|134|154|153|146|152|155|148|170|163|152|150|163|167|187|197|201|223|230|226|232|263|242|277|306|302|327|320|357|355|363|396|367|370|337|382|398|331|337|351|314|320|313|273|295|289|237|241|226|229|240|231|216|195|200|176|207|152|163|157|173|172|180|185|153|178|167|183|203|222|263|257|281|318|376|395|433|396|459|420|479|471|560|463|552|492|511|536|520|488|556|487|561|540|619|608|633|561|628|658|681|648|751|694|692|741|779|715|886|799|968|896|1058|952|1308|1045|1353|1109|1422|1043|1384|936|1140|875|1103|861|933|748|909|613|647|424|397|238|152|104|61|22|19|17|18|6|3|6|3|3|1|2|0|0|2</HistCounts>
      </HistItem>
    </Histograms>
    <Metadata>
      <MDI key="STATISTICS_COUNT">65536.000000</MDI>
      <MDI key="STATISTICS_COVARIANCES">464.0048443960429,1866.116269872242,1409.458981940958</MDI>
      <MDI key="STATISTICS_EXCLUDEDVALUES"></MDI>
      <MDI key="STATISTICS_MAXIMUM">218</MDI>
      <MDI key="STATISTICS_MEAN">148.50196838379</MDI>
      <MDI key="STATISTICS_MEDIAN">163.000000</MDI>
      <MDI key="STATISTICS_MINIMUM">31</MDI>
      <MDI key="STATISTICS_SKIPFACTORX">1</MDI>
      <MDI key="STATISTICS_SKIPFACTORY">1</MDI>
      <MDI key="STATISTICS_STDDEV">43.198567914599</MDI>
    </Metadata>
  </PAMRasterBand>
  <PAMRasterBand band="3">
    <Histograms>
      <HistItem>
        <HistMin>-0.5</HistMin>
        <HistMax>213.5</HistMax>
        <BucketCount>214</BucketCount>
        <IncludeOutOfRange>1</IncludeOutOfRange>
        <Approximate>0</Approximate>
        <HistCounts>0|0|0|0|0|0|0|0|0|0|0|0|0|0|0|0|0|0|0|0|0|0|0|0|0|0|0|0|0|0|0|0|1|0|0|0|1|5|2|9|6|20|32|40|47|61|82|95|118|141|146|130|165|151|174|135|165|153|126|126|139|119|119|121|108|103|113|113|115|106|93|98|94|92|120|92|73|112|94|99|106|100|120|104|115|96|125|117|105|127|128|117|158|130|114|114|133|132|156|148|163|189|208|174|174|213|208|217|204|254|240|261|259|297|280|352|339|339|399|377|357|388|403|373|391|368|353|373|358|332|321|334|359|328|364|352|416|461|542|574|721|748|783|838|859|849|954|829|862|779|855|856|959|896|1079|959|1086|994|1237|1017|1201|992|1108|951|1128|922|1100|942|1141|990|1164|904|1088|839|873|737|741|708|764|596|689|555|647|513|654|608|642|664|753|605|647|441|422|305|270|193|132|49|37|23|15|8|5|3|3|2|2|3|2|0|0|1|0|1</HistCounts>
      </HistItem>
    </Histograms>
    <Metadata>
      <MDI key="STATISTICS_COUNT">65536.000000</MDI>
      <MDI key="STATISTICS_COVARIANCES">465.0088307114268,1409.458981940958,1133.893242107614</MDI>
      <MDI key="STATISTICS_EXCLUDEDVALUES"></MDI>
      <MDI key="STATISTICS_MAXIMUM">213</MDI>
      <MDI key="STATISTICS_MEAN">146.95053100586</MDI>
      <MDI key="STATISTICS_MEDIAN">155.000000</MDI>
      <MDI key="STATISTICS_MINIMUM">32</MDI>
      <MDI key="STATISTICS_SKIPFACTORX">1</MDI>
      <MDI key="STATISTICS_SKIPFACTORY">1</MDI>
      <MDI key="STATISTICS_STDDEV">33.673331318829</MDI>
    </Metadata>
  </PAMRasterBand>
</PAMDataset>
