<PAMDataset>
  <PAMRasterBand band="1">
    <Histograms>
      <HistItem>
        <HistMin>-0.5</HistMin>
        <HistMax>250.5</HistMax>
        <BucketCount>251</BucketCount>
        <IncludeOutOfRange>1</IncludeOutOfRange>
        <Approximate>0</Approximate>
        <HistCounts>0|0|0|0|0|0|0|0|0|0|0|0|0|1|0|1|0|0|0|0|1|1|0|1|1|2|3|1|2|2|0|0|3|1|2|9|2|5|5|0|2|4|9|7|8|8|8|5|6|7|7|10|11|9|10|6|10|5|8|5|6|10|18|10|9|9|13|7|15|11|12|15|27|21|18|19|15|15|27|19|18|25|22|20|22|19|24|20|18|18|21|17|25|23|25|23|31|21|27|20|34|26|29|19|17|28|22|22|17|24|20|24|30|18|20|24|27|37|27|28|33|23|27|29|23|29|27|29|30|35|39|32|32|48|33|41|38|37|31|42|41|36|44|43|40|48|36|57|40|50|50|53|58|55|56|62|66|62|81|65|61|61|68|72|95|83|93|85|86|95|86|89|95|106|105|111|113|126|120|118|120|108|142|129|135|126|137|137|147|162|146|165|160|170|186|180|162|206|240|243|314|319|343|394|630|781|1152|1176|2083|1805|3405|2754|4673|3271|5024|3381|4908|2998|3649|1946|2146|1322|1180|924|891|823|773|726|673|539|546|395|286|284|224|162|135|86|64|56|29|31|20|9|7|3|6|0|3|0|1</HistCounts>
      </HistItem>
    </Histograms>
    <Metadata>
      <MDI key="STATISTICS_COUNT">65536.000000</MDI>
      <MDI key="STATISTICS_COVARIANCES">586.1838472279812,508.3079402309868,477.3064992310775</MDI>
      <MDI key="STATISTICS_EXCLUDEDVALUES"></MDI>
      <MDI key="STATISTICS_MAXIMUM">250</MDI>
      <MDI key="STATISTICS_MEAN">208.27177429199</MDI>
      <MDI key="STATISTICS_MEDIAN">214.000000</MDI>
      <MDI key="STATISTICS_MINIMUM">13</MDI>
      <MDI key="STATISTICS_SKIPFACTORX">1</MDI>
      <MDI key="STATISTICS_SKIPFACTORY">1</MDI>
      <MDI key="STATISTICS_STDDEV">24.211233905524</MDI>
    </Metadata>
  </PAMRasterBand>
  <PAMRasterBand band="2">
    <Histograms>
      <HistItem>
        <HistMin>-0.5</HistMin>
        <HistMax>239.5</HistMax>
        <BucketCount>240</BucketCount>
        <IncludeOutOfRange>1</IncludeOutOfRange>
        <Approximate>0</Approximate>
        <HistCounts>0|0|0|0|0|0|0|0|0|0|0|0|0|0|0|0|0|0|0|0|0|0|0|0|0|0|0|0|0|0|0|0|1|0|1|0|5|7|3|5|17|14|16|22|21|30|49|59|73|71|89|88|107|108|109|136|122|139|125|143|152|178|147|171|142|169|146|155|176|151|171|171|181|179|183|177|197|209|180|194|198|225|205|233|215|210|228|230|219|233|228|219|211|232|228|238|239|215|209|220|220|233|221|194|192|203|189|173|196|160|169|182|181|161|166|169|153|166|163|169|175|155|174|131|154|148|167|137|155|137|150|163|132|141|114|144|143|138|122|129|113|133|126|120|121|128|148|144|134|142|109|136|143|120|160|155|222|217|308|317|408|362|458|372|552|399|517|495|688|648|975|858|1394|1070|1619|1343|1939|1539|2162|1546|1996|1628|2164|1670|2199|1509|2054|1324|1492|1039|1180|812|941|695|776|574|557|463|472|321|336|232|203|144|142|124|145|105|99|83|90|93|111|73|83|65|65|58|60|67|83|55|46|51|46|69|37|55|55|57|35|51|54|22|17|14|4|2|5|1</HistCounts>
      </HistItem>
    </Histograms>
    <Metadata>
      <MDI key="STATISTICS_COUNT">65536.000000</MDI>
      <MDI key="STATISTICS_COVARIANCES">508.3079402309868,1693.073377238802,1256.636464826595</MDI>
      <MDI key="STATISTICS_EXCLUDEDVALUES"></MDI>
      <MDI key="STATISTICS_MAXIMUM">239</MDI>
      <MDI key="STATISTICS_MEAN">159.22924804687</MDI>
      <MDI key="STATISTICS_MEDIAN">176.000000</MDI>
      <MDI key="STATISTICS_MINIMUM">32</MDI>
      <MDI key="STATISTICS_SKIPFACTORX">1</MDI>
      <MDI key="STATISTICS_SKIPFACTORY">1</MDI>
      <MDI key="STATISTICS_STDDEV">41.146972880624</MDI>
    </Metadata>
  </PAMRasterBand>
  <PAMRasterBand band="3">
    <Histograms>
      <HistItem>
        <HistMin>-0.5</HistMin>
        <HistMax>240.5</HistMax>
        <BucketCount>241</BucketCount>
        <IncludeOutOfRange>1</IncludeOutOfRange>
        <Approximate>0</Approximate>
        <HistCounts>0|0|0|0|0|0|0|0|0|0|0|0|0|0|0|0|0|0|0|0|0|0|0|0|0|0|0|0|0|0|0|0|0|0|0|0|2|1|0|2|2|6|0|5|3|4|2|6|11|16|14|22|27|31|34|39|41|53|42|60|47|71|67|88|95|91|113|97|115|130|147|141|164|124|174|128|147|123|129|137|130|138|137|115|145|124|136|115|150|126|149|112|137|133|141|135|152|170|135|142|180|174|173|169|164|173|198|194|225|217|184|190|185|208|192|229|209|251|205|187|231|221|211|234|217|240|215|193|209|223|219|218|226|231|211|226|211|240|208|195|226|216|175|220|217|191|227|239|219|228|231|236|233|229|245|248|235|244|366|373|618|651|1212|1123|2137|1696|3220|2158|3383|2295|3150|2143|3005|2112|2834|1643|2121|1259|1479|835|796|535|518|365|348|301|286|243|257|244|254|243|212|170|241|183|197|144|162|122|139|103|86|110|111|69|76|94|81|69|85|75|46|60|77|71|60|53|71|63|51|64|67|64|55|48|42|30|16|12|9|8|7|4|4|0|1|0|1|1|1</HistCounts>
      </HistItem>
    </Histograms>
    <Metadata>
      <MDI key="STATISTICS_COUNT">65536.000000</MDI>
      <MDI key="STATISTICS_COVARIANCES">477.3064992310775,1256.636464826595,1009.092986398589</MDI>
      <MDI key="STATISTICS_EXCLUDEDVALUES"></MDI>
      <MDI key="STATISTICS_MAXIMUM">240</MDI>
      <MDI key="STATISTICS_MEAN">157.42314147949</MDI>
      <MDI key="STATISTICS_MEDIAN">168.000000</MDI>
      <MDI key="STATISTICS_MINIMUM">36</MDI>
      <MDI key="STATISTICS_SKIPFACTORX">1</MDI>
      <MDI key="STATISTICS_SKIPFACTORY">1</MDI>
      <MDI key="STATISTICS_STDDEV">31.7662239871</MDI>
    </Metadata>
  </PAMRasterBand>
</PAMDataset>
