<PAMDataset>
  <PAMRasterBand band="1">
    <Histograms>
      <HistItem>
        <HistMin>-0.5</HistMin>
        <HistMax>239.5</HistMax>
        <BucketCount>240</BucketCount>
        <IncludeOutOfRange>1</IncludeOutOfRange>
        <Approximate>0</Approximate>
        <HistCounts>17|7|28|36|33|33|17|23|28|28|24|17|32|19|25|39|18|17|15|24|27|25|36|20|18|28|25|26|32|42|31|36|36|32|35|31|25|42|34|33|38|42|31|29|42|45|49|35|50|67|46|46|38|48|40|57|44|47|52|63|96|66|88|67|66|57|60|79|72|64|71|75|68|76|83|75|62|85|68|88|87|65|76|96|108|80|88|91|88|96|88|102|84|96|107|89|92|115|114|97|98|113|124|118|108|110|117|118|134|123|141|142|128|132|129|140|141|134|137|127|127|133|162|164|160|137|152|197|181|200|193|211|192|194|229|198|217|194|259|243|244|256|275|244|284|277|334|328|290|313|312|344|334|378|358|416|383|370|377|407|413|437|465|470|493|500|525|540|497|533|559|541|544|575|617|560|550|591|609|578|647|601|663|617|614|653|667|675|702|669|682|646|671|720|762|715|748|766|799|738|785|751|839|846|905|893|1030|903|1055|984|1208|1014|1223|1039|1174|945|1099|847|926|708|712|556|554|448|439|315|284|219|123|81|59|36|28|16|11|9|5|2|3|1</HistCounts>
      </HistItem>
    </Histograms>
    <Metadata>
      <MDI key="STATISTICS_COUNT">65536.000000</MDI>
      <MDI key="STATISTICS_COVARIANCES">1976.49890696431,1152.879772955255,1144.956820925501</MDI>
      <MDI key="STATISTICS_EXCLUDEDVALUES"></MDI>
      <MDI key="STATISTICS_MAXIMUM">239</MDI>
      <MDI key="STATISTICS_MEAN">173.8016204834</MDI>
      <MDI key="STATISTICS_MEDIAN">186.000000</MDI>
      <MDI key="STATISTICS_MINIMUM">0</MDI>
      <MDI key="STATISTICS_SKIPFACTORX">1</MDI>
      <MDI key="STATISTICS_SKIPFACTORY">1</MDI>
      <MDI key="STATISTICS_STDDEV">44.457832908997</MDI>
    </Metadata>
  </PAMRasterBand>
  <PAMRasterBand band="2">
    <Histograms>
      <HistItem>
        <HistMin>-0.5</HistMin>
        <HistMax>255.5</HistMax>
        <BucketCount>256</BucketCount>
        <IncludeOutOfRange>1</IncludeOutOfRange>
        <Approximate>0</Approximate>
        <HistCounts>0|0|0|0|0|0|0|0|0|0|0|0|1|0|0|1|0|0|0|2|1|0|1|1|0|4|6|11|14|18|34|34|48|79|114|101|158|172|222|224|290|293|331|328|335|383|364|384|396|416|443|445|489|518|471|547|541|581|644|643|654|699|698|752|719|763|818|842|878|833|836|817|866|862|871|828|862|839|849|843|752|748|771|697|699|655|630|624|523|541|530|491|416|422|399|392|363|349|337|280|295|265|243|267|244|238|237|203|199|183|181|181|179|145|153|152|189|168|170|178|182|183|191|187|194|223|240|263|313|280|311|363|359|397|454|396|434|393|454|460|542|520|632|625|756|643|769|681|781|648|714|590|594|479|503|434|426|378|386|323|330|312|309|257|244|209|194|156|178|162|146|147|144|107|121|92|93|98|86|71|73|62|80|53|57|50|64|64|54|51|59|56|68|53|48|53|47|64|43|55|49|51|49|40|55|53|46|55|49|57|48|54|67|52|64|78|79|67|56|67|52|64|61|40|42|55|46|55|49|48|34|51|35|32|42|44|57|48|67|34|35|24|33|24|23|12|10|13|9|15|4|8|6|6|4|1</HistCounts>
      </HistItem>
    </Histograms>
    <Metadata>
      <MDI key="STATISTICS_COUNT">65536.000000</MDI>
      <MDI key="STATISTICS_COVARIANCES">1152.879772955255,2077.59780347478,1743.634245967469</MDI>
      <MDI key="STATISTICS_EXCLUDEDVALUES"></MDI>
      <MDI key="STATISTICS_MAXIMUM">255</MDI>
      <MDI key="STATISTICS_MEAN">104.15328979492</MDI>
      <MDI key="STATISTICS_MEDIAN">89.000000</MDI>
      <MDI key="STATISTICS_MINIMUM">12</MDI>
      <MDI key="STATISTICS_SKIPFACTORX">1</MDI>
      <MDI key="STATISTICS_SKIPFACTORY">1</MDI>
      <MDI key="STATISTICS_STDDEV">45.580673574167</MDI>
    </Metadata>
  </PAMRasterBand>
  <PAMRasterBand band="3">
    <Histograms>
      <HistItem>
        <HistMin>-0.5</HistMin>
        <HistMax>253.5</HistMax>
        <BucketCount>254</BucketCount>
        <IncludeOutOfRange>1</IncludeOutOfRange>
        <Approximate>0</Approximate>
        <HistCounts>0|0|0|0|0|0|0|0|0|0|0|0|0|0|0|0|0|0|0|0|0|0|0|0|1|0|0|0|0|0|0|0|1|1|1|1|3|10|14|14|15|22|25|44|39|57|60|78|88|117|171|166|215|193|275|282|309|318|340|359|370|421|385|439|432|416|505|484|573|524|530|562|594|627|690|614|713|696|769|760|725|795|812|819|822|854|904|764|849|897|903|828|842|801|880|772|784|766|720|754|684|673|619|597|565|593|583|482|452|462|391|361|377|346|303|298|271|275|246|263|213|205|239|215|223|209|199|202|200|194|189|185|159|153|158|173|173|149|167|155|186|206|224|245|346|362|400|437|548|560|714|750|1141|1017|1282|1064|1220|943|1167|850|860|740|650|576|611|488|421|318|291|222|209|166|127|115|109|91|97|91|92|72|66|71|65|65|61|53|43|64|43|44|45|62|57|61|51|58|64|64|57|58|51|61|53|44|59|60|78|48|48|41|38|28|29|28|21|31|18|19|17|31|19|23|12|22|17|17|13|25|18|11|31|19|16|2|12|9|4|9|7|8|6|8|4|6|5|6|4|4|2|7|4|1|4|3</HistCounts>
      </HistItem>
    </Histograms>
    <Metadata>
      <MDI key="STATISTICS_COUNT">65536.000000</MDI>
      <MDI key="STATISTICS_COVARIANCES">1144.956820925501,1743.634245967469,1537.42238954286</MDI>
      <MDI key="STATISTICS_EXCLUDEDVALUES"></MDI>
      <MDI key="STATISTICS_MAXIMUM">253</MDI>
      <MDI key="STATISTICS_MEAN">113.64350891113</MDI>
      <MDI key="STATISTICS_MEDIAN">103.000000</MDI>
      <MDI key="STATISTICS_MINIMUM">24</MDI>
      <MDI key="STATISTICS_SKIPFACTORX">1</MDI>
      <MDI key="STATISTICS_SKIPFACTORY">1</MDI>
      <MDI key="STATISTICS_STDDEV">39.209978188503</MDI>
    </Metadata>
  </PAMRasterBand>
</PAMDataset>
