<PAMDataset>
  <PAMRasterBand band="1">
    <Histograms>
      <HistItem>
        <HistMin>-0.5</HistMin>
        <HistMax>253.5</HistMax>
        <BucketCount>254</BucketCount>
        <IncludeOutOfRange>1</IncludeOutOfRange>
        <Approximate>0</Approximate>
        <HistCounts>0|0|0|0|0|0|0|0|0|0|0|0|0|0|0|0|0|0|0|0|0|0|0|0|0|0|0|0|0|0|0|0|0|0|2|0|3|3|3|2|2|4|4|5|5|5|13|13|14|15|27|19|41|21|25|23|41|20|22|26|24|42|25|22|18|16|19|22|26|26|28|21|20|18|21|25|20|18|25|30|37|31|38|40|34|29|51|49|42|46|55|64|70|59|60|79|72|68|76|91|70|77|88|72|78|90|66|91|100|87|102|101|113|91|108|95|99|78|90|116|118|93|110|126|128|122|106|114|106|130|125|114|136|118|137|125|151|129|150|153|145|150|143|153|157|150|139|189|164|166|180|187|187|168|156|174|178|222|213|210|241|228|229|216|279|256|245|257|286|320|343|348|330|360|384|350|388|388|401|438|461|509|474|511|533|546|592|596|612|641|688|639|681|665|780|748|829|878|866|893|915|978|1000|1089|1077|1201|1209|1286|1401|1432|1427|1431|1506|1491|1578|1382|1360|1275|1295|1162|1146|1119|1060|864|874|838|758|636|571|504|384|404|336|277|251|202|144|121|105|97|76|47|49|26|13|20|17|10|11|1|1|0|0|1</HistCounts>
      </HistItem>
    </Histograms>
    <Metadata>
      <MDI key="STATISTICS_COUNT">65536.000000</MDI>
      <MDI key="STATISTICS_COVARIANCES">1204.611753849296,993.9224357518164,924.4119479668784</MDI>
      <MDI key="STATISTICS_EXCLUDEDVALUES"></MDI>
      <MDI key="STATISTICS_MAXIMUM">253</MDI>
      <MDI key="STATISTICS_MEAN">192.29483032227</MDI>
      <MDI key="STATISTICS_MEDIAN">203.000000</MDI>
      <MDI key="STATISTICS_MINIMUM">34</MDI>
      <MDI key="STATISTICS_SKIPFACTORX">1</MDI>
      <MDI key="STATISTICS_SKIPFACTORY">1</MDI>
      <MDI key="STATISTICS_STDDEV">34.707517252741</MDI>
    </Metadata>
  </PAMRasterBand>
  <PAMRasterBand band="2">
    <Histograms>
      <HistItem>
        <HistMin>-0.5</HistMin>
        <HistMax>234.5</HistMax>
        <BucketCount>235</BucketCount>
        <IncludeOutOfRange>1</IncludeOutOfRange>
        <Approximate>0</Approximate>
        <HistCounts>0|0|0|0|0|0|0|0|0|0|0|0|0|0|0|0|0|0|0|0|0|1|1|0|0|2|6|6|16|18|34|48|59|80|98|130|185|219|239|313|293|306|345|316|329|355|345|320|367|339|331|399|342|337|325|327|330|352|360|374|323|333|335|321|336|332|348|353|348|359|386|326|385|380|357|376|357|396|394|381|383|402|388|405|415|433|412|399|438|416|420|458|425|427|443|471|465|418|470|467|461|475|468|493|467|504|463|484|483|483|464|537|493|498|525|542|550|536|510|572|567|548|576|608|528|577|597|581|603|597|592|584|566|572|565|517|569|549|529|549|580|533|549|479|497|544|523|536|511|541|496|507|498|535|503|498|487|491|485|455|438|415|426|363|387|324|361|289|333|308|280|293|298|272|286|252|263|246|256|267|248|267|226|227|267|213|201|179|200|153|142|124|133|113|107|66|59|68|52|34|31|25|34|20|19|23|23|21|17|16|17|24|33|34|38|21|17|12|13|7|11|9|6|8|13|3|5|8|7|2|8|6|5|3|3</HistCounts>
      </HistItem>
    </Histograms>
    <Metadata>
      <MDI key="STATISTICS_COUNT">65536.000000</MDI>
      <MDI key="STATISTICS_COVARIANCES">993.9224357518164,1739.525353740124,1470.284606636486</MDI>
      <MDI key="STATISTICS_EXCLUDEDVALUES"></MDI>
      <MDI key="STATISTICS_MAXIMUM">234</MDI>
      <MDI key="STATISTICS_MEAN">114.7052154541</MDI>
      <MDI key="STATISTICS_MEDIAN">117.000000</MDI>
      <MDI key="STATISTICS_MINIMUM">21</MDI>
      <MDI key="STATISTICS_SKIPFACTORX">1</MDI>
      <MDI key="STATISTICS_SKIPFACTORY">1</MDI>
      <MDI key="STATISTICS_STDDEV">41.70761745461</MDI>
    </Metadata>
  </PAMRasterBand>
  <PAMRasterBand band="3">
    <Histograms>
      <HistItem>
        <HistMin>-0.5</HistMin>
        <HistMax>226.5</HistMax>
        <BucketCount>227</BucketCount>
        <IncludeOutOfRange>1</IncludeOutOfRange>
        <Approximate>0</Approximate>
        <HistCounts>0|0|0|0|0|0|0|0|0|0|0|0|0|0|0|0|0|0|0|0|0|0|0|0|0|0|0|0|0|2|1|1|0|2|7|10|6|17|12|31|40|49|67|92|106|113|159|167|240|249|286|299|338|356|348|375|402|369|401|358|388|390|368|399|409|397|364|359|430|353|392|424|404|419|370|409|376|376|428|388|408|377|394|426|414|429|421|421|418|447|443|467|441|508|454|472|444|460|485|473|469|494|525|547|522|531|540|522|532|575|510|560|535|550|582|546|603|608|547|614|606|578|609|665|612|627|635|651|651|689|671|663|648|661|645|653|653|619|639|598|637|672|655|626|571|599|579|639|601|584|618|594|549|557|540|513|538|547|473|507|518|465|432|492|374|393|355|391|338|338|348|330|332|269|285|288|249|255|235|211|204|151|180|147|111|121|107|96|91|66|65|37|37|25|42|25|23|19|16|14|10|13|21|25|14|13|15|16|14|6|13|7|7|7|8|3|4|3|3|2|3|4|4|5|4|2|3</HistCounts>
      </HistItem>
    </Histograms>
    <Metadata>
      <MDI key="STATISTICS_COUNT">65536.000000</MDI>
      <MDI key="STATISTICS_COVARIANCES">924.4119479668784,1470.284606636486,1354.223335678807</MDI>
      <MDI key="STATISTICS_EXCLUDEDVALUES"></MDI>
      <MDI key="STATISTICS_MAXIMUM">226</MDI>
      <MDI key="STATISTICS_MEAN">117.09802246094</MDI>
      <MDI key="STATISTICS_MEDIAN">120.000000</MDI>
      <MDI key="STATISTICS_MINIMUM">29</MDI>
      <MDI key="STATISTICS_SKIPFACTORX">1</MDI>
      <MDI key="STATISTICS_SKIPFACTORY">1</MDI>
      <MDI key="STATISTICS_STDDEV">36.799773581896</MDI>
    </Metadata>
  </PAMRasterBand>
</PAMDataset>
