<PAMDataset>
  <PAMRasterBand band="1">
    <Histograms>
      <HistItem>
        <HistMin>-0.5</HistMin>
        <HistMax>240.5</HistMax>
        <BucketCount>241</BucketCount>
        <IncludeOutOfRange>1</IncludeOutOfRange>
        <Approximate>0</Approximate>
        <HistCounts>0|0|0|0|0|0|0|0|0|0|0|0|0|0|0|0|0|0|3|1|1|1|2|4|3|4|5|7|12|10|8|19|21|24|26|29|20|31|21|32|19|27|28|25|30|22|25|22|28|27|18|17|17|22|31|23|35|27|38|43|49|38|58|47|44|43|64|59|49|66|71|73|83|63|67|67|68|62|75|74|79|84|75|72|83|70|86|91|98|92|80|94|97|87|87|79|90|96|104|104|100|81|82|111|114|93|98|108|105|108|116|133|113|105|101|134|122|117|112|127|151|127|131|141|136|131|155|155|176|196|161|200|224|192|217|211|254|228|259|233|255|260|252|268|306|278|311|332|359|335|364|390|420|443|485|499|511|525|569|568|579|598|612|651|711|643|675|714|714|786|705|739|775|765|815|827|840|858|941|881|944|930|1001|998|970|954|1081|1042|1135|1059|1140|1148|1177|1170|1194|1146|1225|1182|1077|1069|1059|983|1018|930|877|810|732|636|627|581|473|520|438|326|330|290|193|183|135|112|114|77|64|48|28|28|17|19|12|6|4|7|2|4|4|4|4|3|0|1|2</HistCounts>
      </HistItem>
    </Histograms>
    <Metadata>
      <MDI key="STATISTICS_COUNT">65536.000000</MDI>
      <MDI key="STATISTICS_COVARIANCES">1207.117759126353,739.6968203773323,686.020709644591</MDI>
      <MDI key="STATISTICS_EXCLUDEDVALUES"></MDI>
      <MDI key="STATISTICS_MAXIMUM">240</MDI>
      <MDI key="STATISTICS_MEAN">171.25154113769</MDI>
      <MDI key="STATISTICS_MEDIAN">180.000000</MDI>
      <MDI key="STATISTICS_MINIMUM">18</MDI>
      <MDI key="STATISTICS_SKIPFACTORX">1</MDI>
      <MDI key="STATISTICS_SKIPFACTORY">1</MDI>
      <MDI key="STATISTICS_STDDEV">34.743600261435</MDI>
    </Metadata>
  </PAMRasterBand>
  <PAMRasterBand band="2">
    <Histograms>
      <HistItem>
        <HistMin>-0.5</HistMin>
        <HistMax>255.5</HistMax>
        <BucketCount>256</BucketCount>
        <IncludeOutOfRange>1</IncludeOutOfRange>
        <Approximate>0</Approximate>
        <HistCounts>0|0|0|0|0|0|0|0|0|0|0|0|0|0|0|0|0|0|1|0|3|1|4|7|8|11|28|31|31|29|53|62|88|99|101|131|159|168|210|200|220|250|250|246|336|285|314|334|363|378|375|393|401|403|449|430|470|441|536|519|511|574|595|588|603|636|693|659|721|723|794|821|851|864|886|932|979|968|1059|1063|1057|1074|1105|1129|1173|1128|1137|1058|1051|1023|1026|960|939|992|908|926|867|762|725|736|672|582|572|547|478|448|442|396|318|328|316|305|261|234|252|214|215|178|169|177|140|132|136|129|113|113|98|107|111|113|112|111|102|106|87|115|104|109|112|96|102|123|112|124|97|130|122|108|126|124|145|136|159|137|174|188|183|171|198|188|233|220|244|219|283|244|239|227|218|227|195|183|224|181|206|195|168|164|155|198|176|152|145|159|138|167|128|107|124|123|123|104|117|100|95|90|108|117|104|87|102|115|121|107|101|88|97|108|88|92|94|70|81|65|58|63|50|55|46|50|40|30|36|30|35|27|35|26|21|20|18|29|28|21|22|22|17|25|30|20|41|26|40|19|23|22|20|26|30|33|18|15|11|11|9|11</HistCounts>
      </HistItem>
    </Histograms>
    <Metadata>
      <MDI key="STATISTICS_COUNT">65536.000000</MDI>
      <MDI key="STATISTICS_COVARIANCES">739.6968203773323,1925.570074712744,1484.968240573459</MDI>
      <MDI key="STATISTICS_EXCLUDEDVALUES"></MDI>
      <MDI key="STATISTICS_MAXIMUM">255</MDI>
      <MDI key="STATISTICS_MEAN">99.011154174804</MDI>
      <MDI key="STATISTICS_MEDIAN">87.000000</MDI>
      <MDI key="STATISTICS_MINIMUM">18</MDI>
      <MDI key="STATISTICS_SKIPFACTORX">1</MDI>
      <MDI key="STATISTICS_SKIPFACTORY">1</MDI>
      <MDI key="STATISTICS_STDDEV">43.88131806034</MDI>
    </Metadata>
  </PAMRasterBand>
  <PAMRasterBand band="3">
    <Histograms>
      <HistItem>
        <HistMin>-0.5</HistMin>
        <HistMax>255.5</HistMax>
        <BucketCount>256</BucketCount>
        <IncludeOutOfRange>1</IncludeOutOfRange>
        <Approximate>0</Approximate>
        <HistCounts>0|0|0|0|0|0|0|0|0|0|0|0|0|0|0|0|0|0|0|0|0|0|0|0|0|0|0|0|0|0|0|1|0|0|1|2|2|3|10|9|13|16|22|28|35|35|46|64|69|80|113|101|116|155|130|185|196|225|238|247|254|275|328|303|347|388|366|379|424|439|492|490|482|532|543|483|501|553|559|612|604|582|673|671|684|762|830|767|799|812|846|914|931|972|981|1016|1025|1061|1139|1074|1131|1146|1151|1142|1128|1139|1071|1084|1024|949|951|889|918|846|808|764|787|624|640|620|530|534|480|462|411|374|342|278|319|264|291|248|240|268|211|182|204|183|179|152|162|170|154|158|151|152|169|175|204|192|185|212|226|199|293|311|401|453|516|402|463|356|369|332|320|274|301|279|271|236|239|204|197|179|172|181|153|143|116|123|113|137|137|136|105|112|109|104|94|102|94|94|71|74|60|57|57|59|45|40|31|43|39|26|21|34|13|23|37|13|18|18|14|26|26|16|15|25|20|26|26|12|26|9|22|13|18|14|15|9|12|8|7|6|13|12|7|12|12|7|8|8|9|6|11|17|14|16|19|19|13|12|19|6|14|9</HistCounts>
      </HistItem>
    </Histograms>
    <Metadata>
      <MDI key="STATISTICS_COUNT">65536.000000</MDI>
      <MDI key="STATISTICS_COVARIANCES">686.020709644591,1484.968240573459,1196.802576142507</MDI>
      <MDI key="STATISTICS_EXCLUDEDVALUES"></MDI>
      <MDI key="STATISTICS_MAXIMUM">255</MDI>
      <MDI key="STATISTICS_MEAN">110.16874694824</MDI>
      <MDI key="STATISTICS_MEDIAN">104.000000</MDI>
      <MDI key="STATISTICS_MINIMUM">31</MDI>
      <MDI key="STATISTICS_SKIPFACTORX">1</MDI>
      <MDI key="STATISTICS_SKIPFACTORY">1</MDI>
      <MDI key="STATISTICS_STDDEV">34.594834529775</MDI>
    </Metadata>
  </PAMRasterBand>
</PAMDataset>
